thop/__init__.py
thop/fx_profile.py
thop/onnx_profile.py
thop/profile.py
thop/rnn_hooks.py
thop/utils.py
thop/vision/__init__.py
thop/vision/basic_hooks.py
thop/vision/calc_func.py
thop/vision/efficientnet.py
thop/vision/onnx_counter.py
thop-0.1.0.post2207010342.dist-info/LICENSE
thop-0.1.0.post2207010342.dist-info/METADATA
thop-0.1.0.post2207010342.dist-info/WHEEL
thop-0.1.0.post2207010342.dist-info/top_level.txt
thop-0.1.0.post2207010342.dist-info/zip-safe
thop-0.1.0.post2207010342.dist-info/RECORD
