Metadata-Version: 2.1
Name: thop
Version: 0.1.0-2207010342
Summary: A tool to count the FLOPs of PyTorch model.
Home-page: https://github.com/Lyken17/pytorch-OpCounter/
Author: Ligeng Zhu
Author-email: ligeng.zhu+github@gmail.com
License: MIT
Platform: UNKNOWN
Classifier: Programming Language :: Python :: 3
License-File: LICENSE
Requires-Dist: torch
